.gitignore
CHANGES.rst
LICENSE.txt
MANIFEST.in
README.rst
setup.py
django_bitcoin/BCAddressField.py
django_bitcoin/__init__.py
django_bitcoin/admin.py
django_bitcoin/context_processors.py
django_bitcoin/currency.py
django_bitcoin/forms.py
django_bitcoin/mock_bitcoin_objects.py
django_bitcoin/models.py
django_bitcoin/pywallet.py
django_bitcoin/requirements.txt
django_bitcoin/settings.py
django_bitcoin/test_zero_confirmation.py
django_bitcoin/tests.py
django_bitcoin/urls.py
django_bitcoin/utils.py
django_bitcoin/views.py
django_bitcoin.egg-info/PKG-INFO
django_bitcoin.egg-info/SOURCES.txt
django_bitcoin.egg-info/dependency_links.txt
django_bitcoin.egg-info/top_level.txt
django_bitcoin/jsonrpc/__init__.py
django_bitcoin/jsonrpc/authproxy.py
django_bitcoin/jsonrpc/json.py
django_bitcoin/jsonrpc/proxy.py
django_bitcoin/management/__init__.py
django_bitcoin/management/commands/CheckDbIntegrity.py
django_bitcoin/management/commands/CheckTransactions.py
django_bitcoin/management/commands/FixLastBalancesConcurrency.py
django_bitcoin/management/commands/FlushBitcoin.py
django_bitcoin/management/commands/GetHistoricalRates.py
django_bitcoin/management/commands/__init__.py
django_bitcoin/migrations/0001_initial.py
django_bitcoin/migrations/0002_auto__add_field_bitcoinaddress_label.py
django_bitcoin/migrations/0003_auto__add_unique_bitcoinaddress_address.py
django_bitcoin/migrations/0004_auto__add_field_bitcoinaddress_least_received_confirmed.py
django_bitcoin/migrations/0005_auto__add_field_bitcoinaddress_wallet.py
django_bitcoin/migrations/0006_auto__add_field_wallet_transaction_counter.py
django_bitcoin/migrations/0007_auto__add_field_wallet_last_balance.py
django_bitcoin/migrations/0008_auto__add_historicalprice__chg_field_wallet_last_balance.py
django_bitcoin/migrations/__init__.py
django_bitcoin/templates/__init__.py
django_bitcoin/templates/bitcoin_payment_qr.html
django_bitcoin/templates/wallet_history.html
django_bitcoin/templates/wallet_tagline.html
django_bitcoin/templatetags/__init__.py
django_bitcoin/templatetags/currency_conversions.py