Metadata-Version: 1.1
Name: django-bitcoin
Version: 0.2
Summary: Bitcoin application integration for Django web framework
Home-page: https://github.com/kangasbros/django-bitcoin
Author: Jeremias Kangas
Author-email: UNKNOWN
License: MIT
Platform: UNKNOWN
Requires: qrcode (>2.3.1)
Requires: South (>0.7.4)
